MANIFEST.in
README.md
setup.py
pyipmeta/__init__.py
pyipmeta/dbidx.py
pyipmeta/pyipmeta.py
pyipmeta.egg-info/PKG-INFO
pyipmeta.egg-info/SOURCES.txt
pyipmeta.egg-info/dependency_links.txt
pyipmeta.egg-info/entry_points.txt
pyipmeta.egg-info/requires.txt
pyipmeta.egg-info/top_level.txt
src/_pyipmeta_ipmeta.c
src/_pyipmeta_ipmeta.h
src/_pyipmeta_module.c
src/_pyipmeta_provider.c
src/_pyipmeta_provider.h
src/_pyipmeta_record.c
src/_pyipmeta_record.h
src/pyutils.h
test/_pyipmeta_test.py
test/maxmind/2017-03-16.GeoLiteCity-Blocks.csv.gz
test/maxmind/2017-03-16.GeoLiteCity-Location.csv.gz
test/pfx2as/routeviews-rv2-20170329-0200.pfx2as.gz