Metadata-Version: 1.1
Name: pyipmeta
Version: 3.0.0
Summary: A Python interface to libipmeta
Home-page: http://github.com/CAIDA/pyipmeta
Author: Alistair King
Author-email: corsaro-info@caida.org
License: GPLv3
Keywords: _pyipmeta pyipmeta geolocation pfx2as
Platform: UNKNOWN
Classifier: Development Status :: 5 - Production/Stable
Classifier: Environment :: Console
Classifier: Intended Audience :: Science/Research
Classifier: Intended Audience :: System Administrators
Classifier: Intended Audience :: Telecommunications Industry
Classifier: Intended Audience :: Information Technology
Classifier: License :: OSI Approved :: GNU General Public License v3 (GPLv3)
Classifier: Operating System :: POSIX
